systemic_risk/BrownianBridgeSim.py
systemic_risk/BrownianBridgeSimStoVol.py
systemic_risk/Liquidity.py
systemic_risk/__init__.py
systemic_risk-0.0.10.dist-info/LICENSE
systemic_risk-0.0.10.dist-info/METADATA
systemic_risk-0.0.10.dist-info/WHEEL
systemic_risk-0.0.10.dist-info/top_level.txt
systemic_risk-0.0.10.dist-info/RECORD
