Metadata-Version: 2.1
Name: systemic_risk
Version: 0.0.10
Summary: A package for calculating systemic risk in the market
Home-page: https://github.com/gophronesis/systemic_risk
Author: Flynn Chen
Author-email: flynn.chen@yale.edu
License: UNKNOWN
Project-URL: Bug Tracker, https://github.com/gophronesis/systemic_risk/issues
Platform: UNKNOWN
Classifier: Programming Language :: Python :: 3
Classifier: License :: OSI Approved :: MIT License
Classifier: Operating System :: OS Independent
Requires-Python: >=3.6
License-File: LICENSE
